rustpyppr-0.1.2.dist-info/METADATA
rustpyppr-0.1.2.dist-info/WHEEL
rustpyppr/__init__.py
rustpyppr/__init__.pyi
rustpyppr/py.typed
rustpyppr/rustpyppr.cpython-311-x86_64-linux-gnu.so
rustpyppr-0.1.2.dist-info/RECORD
