Metadata-Version: 2.1
Name: rustpyppr
Version: 0.1.2
